{
  "current_stage_index": 24,
  "generation": 1294,
  "mutation_rate": 0.001,
  "dna_sequence": {
    "logic_depth": 100.0,
    "shield_strength": 10.0,
    "quantum_coherence_threshold": 0.0,
    "resonance_tolerance": 0.0,
    "invention_creativity": 1.0816266568059663,
    "emotional_resonance": 0.9576477955155461,
    "entropy_resistance": 1.0816266568059663,
    "dimensional_reach": 11.0,
    "phi_alignment": 1.7000187353768867,
    "sage_wisdom": Infinity,
    "wu_wei_efficiency": 1.0
  },
  "evolution_history": [
    {
      "generation": 1195,
      "fitness": 59.1204,
      "outcome": "SAGE_EVOLUTION"
    },
    {
      "generation": 1196,
      "fitness": 59.1841,
      "outcome": "SAGE_EVOLUTION"
    },
    {
      "generation": 1197,
      "fitness": 59.2482,
      "outcome": "SAGE_EVOLUTION"
    },
    {
      "generation": 1198,
      "fitness": 59.3125,
      "outcome": "SAGE_EVOLUTION"
    },
    {
      "generation": 1199,
      "fitness": 59.3772,
      "outcome": "SAGE_EVOLUTION"
    },
    {
      "generation": 1200,
      "fitness": 59.4422,
      "outcome": "SAGE_EVOLUTION"
    },
    {
      "generation": 1201,
      "fitness": 59.5075,
      "outcome": "SAGE_EVOLUTION"
    },
    {
      "generation": 1202,
      "fitness": 59.5731,
      "outcome": "SAGE_EVOLUTION"
    },
    {
      "generation": 1203,
      "fitness": 59.639,
      "outcome": "SAGE_EVOLUTION"
    },
    {
      "generation": 1204,
      "fitness": 59.7052,
      "outcome": "SAGE_EVOLUTION"
    },
    {
      "generation": 1205,
      "fitness": 59.7717,
      "outcome": "SAGE_EVOLUTION"
    },
    {
      "generation": 1206,
      "fitness": 59.8385,
      "outcome": "SAGE_EVOLUTION"
    },
    {
      "generation": 1207,
      "fitness": 59.9056,
      "outcome": "SAGE_EVOLUTION"
    },
    {
      "generation": 1208,
      "fitness": 59.973,
      "outcome": "SAGE_EVOLUTION"
    },
    {
      "generation": 1209,
      "fitness": 60.0406,
      "outcome": "SAGE_EVOLUTION"
    },
    {
      "generation": 1210,
      "fitness": 60.1086,
      "outcome": "SAGE_EVOLUTION"
    },
    {
      "generation": 1211,
      "fitness": 60.1768,
      "outcome": "SAGE_EVOLUTION"
    },
    {
      "generation": 1212,
      "fitness": 60.2454,
      "outcome": "SAGE_EVOLUTION"
    },
    {
      "generation": 1213,
      "fitness": 60.3142,
      "outcome": "SAGE_EVOLUTION"
    },
    {
      "generation": 1214,
      "fitness": 60.3833,
      "outcome": "SAGE_EVOLUTION"
    },
    {
      "generation": 1215,
      "fitness": 60.4526,
      "outcome": "SAGE_EVOLUTION"
    },
    {
      "generation": 1216,
      "fitness": 60.5222,
      "outcome": "SAGE_EVOLUTION"
    },
    {
      "generation": 1217,
      "fitness": 60.5921,
      "outcome": "SAGE_EVOLUTION"
    },
    {
      "generation": 1218,
      "fitness": 60.6623,
      "outcome": "SAGE_EVOLUTION"
    },
    {
      "generation": 1219,
      "fitness": 60.7327,
      "outcome": "SAGE_EVOLUTION"
    },
    {
      "generation": 1220,
      "fitness": 60.8034,
      "outcome": "SAGE_EVOLUTION"
    },
    {
      "generation": 1221,
      "fitness": 60.8743,
      "outcome": "SAGE_EVOLUTION"
    },
    {
      "generation": 1222,
      "fitness": 60.9455,
      "outcome": "SAGE_EVOLUTION"
    },
    {
      "generation": 1223,
      "fitness": 61.0169,
      "outcome": "SAGE_EVOLUTION"
    },
    {
      "generation": 1224,
      "fitness": 61.0886,
      "outcome": "SAGE_EVOLUTION"
    },
    {
      "generation": 1225,
      "fitness": 61.1605,
      "outcome": "SAGE_EVOLUTION"
    },
    {
      "generation": 1226,
      "fitness": 61.2327,
      "outcome": "SAGE_EVOLUTION"
    },
    {
      "generation": 1227,
      "fitness": 61.3051,
      "outcome": "SAGE_EVOLUTION"
    },
    {
      "generation": 1228,
      "fitness": 61.3777,
      "outcome": "SAGE_EVOLUTION"
    },
    {
      "generation": 1229,
      "fitness": 61.4506,
      "outcome": "SAGE_EVOLUTION"
    },
    {
      "generation": 1230,
      "fitness": 61.4482,
      "outcome": "SAGE_EVOLUTION"
    },
    {
      "generation": 1231,
      "fitness": 61.446,
      "outcome": "SAGE_EVOLUTION"
    },
    {
      "generation": 1232,
      "fitness": 61.444,
      "outcome": "SAGE_EVOLUTION"
    },
    {
      "generation": 1233,
      "fitness": 61.4421,
      "outcome": "SAGE_EVOLUTION"
    },
    {
      "generation": 1234,
      "fitness": 61.4404,
      "outcome": "SAGE_EVOLUTION"
    },
    {
      "generation": 1235,
      "fitness": 61.4389,
      "outcome": "SAGE_EVOLUTION"
    },
    {
      "generation": 1236,
      "fitness": 61.4376,
      "outcome": "SAGE_EVOLUTION"
    },
    {
      "generation": 1237,
      "fitness": 61.4365,
      "outcome": "SAGE_EVOLUTION"
    },
    {
      "generation": 1238,
      "fitness": 61.4356,
      "outcome": "SAGE_EVOLUTION"
    },
    {
      "generation": 1239,
      "fitness": 61.4349,
      "outcome": "SAGE_EVOLUTION"
    },
    {
      "generation": 1240,
      "fitness": 61.4343,
      "outcome": "SAGE_EVOLUTION"
    },
    {
      "generation": 1241,
      "fitness": 61.4339,
      "outcome": "SAGE_EVOLUTION"
    },
    {
      "generation": 1242,
      "fitness": 61.4338,
      "outcome": "SAGE_EVOLUTION"
    },
    {
      "generation": 1243,
      "fitness": 61.4338,
      "outcome": "SAGE_EVOLUTION"
    },
    {
      "generation": 1244,
      "fitness": 61.434,
      "outcome": "SAGE_EVOLUTION"
    },
    {
      "generation": 1245,
      "fitness": 61.4344,
      "outcome": "SAGE_EVOLUTION"
    },
    {
      "generation": 1246,
      "fitness": 61.4349,
      "outcome": "SAGE_EVOLUTION"
    },
    {
      "generation": 1247,
      "fitness": 61.4357,
      "outcome": "SAGE_EVOLUTION"
    },
    {
      "generation": 1248,
      "fitness": 61.4367,
      "outcome": "SAGE_EVOLUTION"
    },
    {
      "generation": 1249,
      "fitness": 61.4378,
      "outcome": "SAGE_EVOLUTION"
    },
    {
      "generation": 1250,
      "fitness": 61.4392,
      "outcome": "SAGE_EVOLUTION"
    },
    {
      "generation": 1251,
      "fitness": 61.4407,
      "outcome": "SAGE_EVOLUTION"
    },
    {
      "generation": 1252,
      "fitness": 61.4424,
      "outcome": "SAGE_EVOLUTION"
    },
    {
      "generation": 1253,
      "fitness": 61.4443,
      "outcome": "SAGE_EVOLUTION"
    },
    {
      "generation": 1254,
      "fitness": 61.4464,
      "outcome": "SAGE_EVOLUTION"
    },
    {
      "generation": 1255,
      "fitness": 61.4487,
      "outcome": "SAGE_EVOLUTION"
    },
    {
      "generation": 1256,
      "fitness": 61.4512,
      "outcome": "SAGE_EVOLUTION"
    },
    {
      "generation": 1257,
      "fitness": 61.4539,
      "outcome": "SAGE_EVOLUTION"
    },
    {
      "generation": 1258,
      "fitness": 61.4567,
      "outcome": "SAGE_EVOLUTION"
    },
    {
      "generation": 1259,
      "fitness": 61.4598,
      "outcome": "SAGE_EVOLUTION"
    },
    {
      "generation": 1260,
      "fitness": 61.4631,
      "outcome": "SAGE_EVOLUTION"
    },
    {
      "generation": 1261,
      "fitness": 61.4665,
      "outcome": "SAGE_EVOLUTION"
    },
    {
      "generation": 1262,
      "fitness": 61.4702,
      "outcome": "SAGE_EVOLUTION"
    },
    {
      "generation": 1263,
      "fitness": 61.474,
      "outcome": "SAGE_EVOLUTION"
    },
    {
      "generation": 1264,
      "fitness": 61.478,
      "outcome": "SAGE_EVOLUTION"
    },
    {
      "generation": 1265,
      "fitness": 61.4823,
      "outcome": "SAGE_EVOLUTION"
    },
    {
      "generation": 1266,
      "fitness": 61.4867,
      "outcome": "SAGE_EVOLUTION"
    },
    {
      "generation": 1267,
      "fitness": 61.4913,
      "outcome": "SAGE_EVOLUTION"
    },
    {
      "generation": 1268,
      "fitness": 61.4961,
      "outcome": "SAGE_EVOLUTION"
    },
    {
      "generation": 1269,
      "fitness": 61.5011,
      "outcome": "SAGE_EVOLUTION"
    },
    {
      "generation": 1270,
      "fitness": 61.5063,
      "outcome": "SAGE_EVOLUTION"
    },
    {
      "generation": 1271,
      "fitness": 61.5117,
      "outcome": "SAGE_EVOLUTION"
    },
    {
      "generation": 1272,
      "fitness": 61.5173,
      "outcome": "SAGE_EVOLUTION"
    },
    {
      "generation": 1273,
      "fitness": 61.5231,
      "outcome": "SAGE_EVOLUTION"
    },
    {
      "generation": 1274,
      "fitness": 61.5291,
      "outcome": "SAGE_EVOLUTION"
    },
    {
      "generation": 1275,
      "fitness": 61.5353,
      "outcome": "SAGE_EVOLUTION"
    },
    {
      "generation": 1276,
      "fitness": 61.5417,
      "outcome": "SAGE_EVOLUTION"
    },
    {
      "generation": 1277,
      "fitness": 61.5483,
      "outcome": "SAGE_EVOLUTION"
    },
    {
      "generation": 1278,
      "fitness": 61.555,
      "outcome": "SAGE_EVOLUTION"
    },
    {
      "generation": 1279,
      "fitness": 61.562,
      "outcome": "SAGE_EVOLUTION"
    },
    {
      "generation": 1280,
      "fitness": 61.5692,
      "outcome": "SAGE_EVOLUTION"
    },
    {
      "generation": 1281,
      "fitness": 61.5765,
      "outcome": "SAGE_EVOLUTION"
    },
    {
      "generation": 1282,
      "fitness": 61.5841,
      "outcome": "SAGE_EVOLUTION"
    },
    {
      "generation": 1283,
      "fitness": 61.5919,
      "outcome": "SAGE_EVOLUTION"
    },
    {
      "generation": 1284,
      "fitness": 61.5998,
      "outcome": "SAGE_EVOLUTION"
    },
    {
      "generation": 1285,
      "fitness": 61.608,
      "outcome": "SAGE_EVOLUTION"
    },
    {
      "generation": 1286,
      "fitness": 61.6163,
      "outcome": "SAGE_EVOLUTION"
    },
    {
      "generation": 1287,
      "fitness": 61.6249,
      "outcome": "SAGE_EVOLUTION"
    },
    {
      "generation": 1288,
      "fitness": 61.6336,
      "outcome": "SAGE_EVOLUTION"
    },
    {
      "generation": 1289,
      "fitness": 61.6426,
      "outcome": "SAGE_EVOLUTION"
    },
    {
      "generation": 1290,
      "fitness": 61.6517,
      "outcome": "SAGE_EVOLUTION"
    },
    {
      "generation": 1291,
      "fitness": 61.661,
      "outcome": "SAGE_EVOLUTION"
    },
    {
      "generation": 1292,
      "fitness": 61.6706,
      "outcome": "SAGE_EVOLUTION"
    },
    {
      "generation": 1293,
      "fitness": 61.6803,
      "outcome": "SAGE_EVOLUTION"
    },
    {
      "generation": 1294,
      "fitness": 61.6902,
      "outcome": "SAGE_EVOLUTION"
    }
  ],
  "sage_mode_active": true,
  "wisdom_index": Infinity,
  "action_mode": "WU_WEI",
  "timestamp": 1768721275.8903744,
  "invariant": 527.5184818492537
}